<annotation>
	<folder></folder>
	<filename>13912.jpg</filename>
	<path>13912.jpg</path>
	<source>
		<database>roboflow.ai</database>
	</source>
	<size>
		<width>300</width>
		<height>300</height>
		<depth>3</depth>
	</size>
	<segmented>0</segmented>
	<object>
		<name>drone</name>
		<pose>Unspecified</pose>
		<truncated>0</truncated>
		<difficult>0</difficult>
		<bndbox>
			<xmin>23</xmin>
			<ymin>51</ymin>
                        <xmax>74</xmax>
			<ymax>102</ymax>
		</bndbox>
	</object>
</annotation>
