<annotation>
	<folder></folder>
	<filename>7069.jpg</filename>
	<path>7069.jpg</path>
	<source>
		<database>roboflow.ai</database>
	</source>
	<size>
		<width>300</width>
		<height>300</height>
		<depth>3</depth>
	</size>
	<segmented>0</segmented>
	<object>
		<name>drone</name>
		<pose>Unspecified</pose>
		<truncated>0</truncated>
		<difficult>0</difficult>
		<bndbox>
			<xmin>16</xmin>
			<ymin>152</ymin>
                        <xmax>89</xmax>
			<ymax>225</ymax>
		</bndbox>
	</object>
</annotation>
