<annotation>
	<folder>drone</folder>
	<filename>drone492.jpg</filename>
	<path>/home/santhui/PythonProject/My_Project/duplicate_images_remove/dataset/drone/drone492.jpg</path>
	<source>
		<database>Unknown</database>
	</source>
	<size>
		<width>600</width>
		<height>600</height>
		<depth>3</depth>
	</size>
	<segmented>0</segmented>
	<object>
		<name>drone</name>
		<pose>Unspecified</pose>
		<truncated>0</truncated>
		<difficult>0</difficult>
		<bndbox>
			<xmin>209</xmin>
			<ymin>46</ymin>
			<xmax>308</xmax>
			<ymax>165</ymax>
		</bndbox>
	</object>
</annotation>
